mol_adme.py
mol_adme-1.0.0.dist-info/METADATA
mol_adme-1.0.0.dist-info/WHEEL
mol_adme-1.0.0.dist-info/entry_points.txt
mol_adme-1.0.0.dist-info/top_level.txt
mol_adme-1.0.0.dist-info/RECORD
