Metadata-Version: 2.4
Name: mol-adme
Version: 1.0.0
Summary: Offline ADME & BOILED-Egg batch tool for molecules
Home-page: https://pypi.org/project/mol-adme/
Author: Sai Eswar M
Author-email: msaieswar2002@gmail.com
Classifier: Programming Language :: Python :: 3
Classifier: License :: OSI Approved :: MIT License
Classifier: Operating System :: OS Independent
Requires-Python: >=3.10
Requires-Dist: rdkit-pypi==2023.3.1b1
Requires-Dist: pandas>=2.0.3
Requires-Dist: matplotlib>=3.7.1
Dynamic: author
Dynamic: author-email
Dynamic: classifier
Dynamic: description
Dynamic: description-content-type
Dynamic: home-page
Dynamic: requires-dist
Dynamic: requires-python
Dynamic: summary
